AUTHORS.txt
CHANGES.txt
LICENSE.txt
MANIFEST.in
README.txt
setup.cfg
setup.py
doc/Makefile
doc/source/blkop.rst
doc/source/conf.py
doc/source/index.rst
doc/source/intro.rst
doc/source/linop.rst
linop/__init__.py
linop/blkop.py
linop/linop.py
linop.egg-info/PKG-INFO
linop.egg-info/SOURCES.txt
linop.egg-info/dependency_links.txt
linop.egg-info/not-zip-safe
linop.egg-info/top_level.txt