Metadata-Version: 1.1
Name: linop
Version: 0.8.2
Summary: A pythonic abstraction for linear mathematical operators
Home-page: https://github.com/ghisvail/linop
Author: Ghislain Vaillant
Author-email: ghisvail@gmail.com
License: BSD
Keywords: linear,operator,mathematics
Platform: UNKNOWN
Classifier: Development Status :: 4 - Beta
Classifier: Intended Audience :: Developers
Classifier: Intended Audience :: Science/Research
Classifier: License :: OSI Approved :: BSD License
Classifier: Operating System :: OS Independent
Classifier: Programming Language :: Python
Classifier: Programming Language :: Python :: 3
Classifier: Topic :: Scientific/Engineering
Classifier: Topic :: Software Development
